{"https___kanliveicy_media_kan_org_il_icy_kankolhamusica_mp3.m3u":{"date":"2026-02-22","count":5,"error":"[tcp @ 0x55dd79578f40] Connection to tcp://kanliveicy.media.kan.org.il:443 failed: Connection refused\nhttps://kanliveicy.media.kan.org.il/icy/kankolhamusica_mp3: Connection refused"},"https___online_extrafm_lt_8443_extrafm_mp3.m3u":{"date":"2026-02-22","count":5,"error":"[tcp @ 0x557714badf40] Connection to tcp://online.extrafm.lt:8443 failed: Connection timed out\nhttps://online.extrafm.lt:8443/extrafm.mp3: Connection timed out"}}